{
  "tasks": [
    {
      "title": "Primeira Tarefa 2",
      "completed": false,
      "createdAt": 1713373773860,
      "updatedAt": null,
      "id": 18,
      "userId": "2",
      "updateAt": 1713375610833
    },
    {
      "title": "Segunda Tarefa",
      "completed": false,
      "createdAt": 1713373780651,
      "updatedAt": null,
      "id": 19,
      "userId": "2",
      "updateAt": 1713374036203
    },
    {
      "title": "ABC",
      "completed": false,
      "createdAt": 1713383161497,
      "updatedAt": null,
      "id": 20,
      "userId": "2"
    },
    {
      "title": "ABC",
      "completed": false,
      "createdAt": 1713383242225,
      "updatedAt": null,
      "id": 21,
      "userId": "2"
    },
    {
      "title": "ABC",
      "completed": false,
      "createdAt": 1713384440473,
      "updatedAt": null,
      "id": 22,
      "userId": "2"
    },
    {
      "title": "aa",
      "completed": false,
      "createdAt": 1713384467064,
      "updatedAt": null,
      "id": 23,
      "userId": "2"
    },
    {
      "title": "ABC",
      "completed": false,
      "createdAt": 1713384487528,
      "updatedAt": null,
      "id": 24,
      "userId": "2"
    }
  ],
  "users": [
    {
      "id": 1,
      "email": "daniel@server"
    },
    {
      "id": 2,
      "email": "maria@server"
    },
    {
      "id": 3,
      "email": "joao@server"
    }
  ]
}